{
  "version": 1,
  "generatedAt": "2026-07-23T17:00:00.000Z",
  "coverage": "seed",
  "instruments": [
    {"id":"equity-us-aapl-xnas","name":"Apple Inc.","assetClass":"equity","status":"active","ticker":"AAPL","exchangeMic":"XNAS","exchangeName":"Nasdaq","country":"US","region":"north-america","currency":"USD","sector":"technology","industry":"consumer-electronics","identifiers":[{"type":"ticker","value":"AAPL","source":"nasdaq"}],"primarySources":["sec","nasdaq"],"lastVerifiedAt":null},
    {"id":"equity-us-msft-xnas","name":"Microsoft Corporation","assetClass":"equity","status":"active","ticker":"MSFT","exchangeMic":"XNAS","exchangeName":"Nasdaq","country":"US","region":"north-america","currency":"USD","sector":"technology","industry":"software","identifiers":[{"type":"ticker","value":"MSFT","source":"nasdaq"}],"primarySources":["sec","nasdaq"],"lastVerifiedAt":null},
    {"id":"equity-us-nvda-xnas","name":"NVIDIA Corporation","assetClass":"equity","status":"active","ticker":"NVDA","exchangeMic":"XNAS","exchangeName":"Nasdaq","country":"US","region":"north-america","currency":"USD","sector":"technology","industry":"semiconductors","identifiers":[{"type":"ticker","value":"NVDA","source":"nasdaq"}],"primarySources":["sec","nasdaq"],"lastVerifiedAt":null},
    {"id":"equity-de-sie-xetr","name":"Siemens AG","assetClass":"equity","status":"active","ticker":"SIE","exchangeMic":"XETR","exchangeName":"Xetra","country":"DE","region":"europe","currency":"EUR","sector":"industrials","industry":"industrial-conglomerates","identifiers":[{"type":"ticker","value":"SIE","source":"deutsche-boerse"}],"primarySources":["deutsche-boerse"],"lastVerifiedAt":null},
    {"id":"equity-fr-mc-xpar","name":"LVMH Moet Hennessy Louis Vuitton SE","assetClass":"equity","status":"active","ticker":"MC","exchangeMic":"XPAR","exchangeName":"Euronext Paris","country":"FR","region":"europe","currency":"EUR","sector":"consumer-discretionary","industry":"luxury-goods","identifiers":[{"type":"ticker","value":"MC","source":"euronext"}],"primarySources":["euronext"],"lastVerifiedAt":null},
    {"id":"equity-it-enel-xmil","name":"Enel S.p.A.","assetClass":"equity","status":"active","ticker":"ENEL","exchangeMic":"XMIL","exchangeName":"Euronext Milan","country":"IT","region":"europe","currency":"EUR","sector":"utilities","industry":"electric-utilities","identifiers":[{"type":"ticker","value":"ENEL","source":"euronext"}],"primarySources":["euronext"],"lastVerifiedAt":null},
    {"id":"equity-jp-7203-xtks","name":"Toyota Motor Corporation","assetClass":"equity","status":"active","ticker":"7203","exchangeMic":"XTKS","exchangeName":"Tokyo Stock Exchange","country":"JP","region":"asia-pacific","currency":"JPY","sector":"consumer-discretionary","industry":"automobiles","identifiers":[{"type":"ticker","value":"7203","source":"jpx"}],"primarySources":["jpx"],"lastVerifiedAt":null},
    {"id":"equity-cn-600519-xshg","name":"Kweichow Moutai Co., Ltd.","assetClass":"equity","status":"active","ticker":"600519","exchangeMic":"XSHG","exchangeName":"Shanghai Stock Exchange","country":"CN","region":"asia-pacific","currency":"CNY","sector":"consumer-staples","industry":"beverages","identifiers":[{"type":"ticker","value":"600519","source":"sse"}],"primarySources":["sse"],"lastVerifiedAt":null},
    {"id":"equity-in-reliance-xnse","name":"Reliance Industries Limited","assetClass":"equity","status":"active","ticker":"RELIANCE","exchangeMic":"XNSE","exchangeName":"National Stock Exchange of India","country":"IN","region":"asia-pacific","currency":"INR","sector":"energy","industry":"integrated-energy","identifiers":[{"type":"ticker","value":"RELIANCE","source":"nse-india"}],"primarySources":["nse-india"],"lastVerifiedAt":null},
    {"id":"equity-br-petr4-bvmf","name":"Petroleo Brasileiro S.A. Petrobras","assetClass":"equity","status":"active","ticker":"PETR4","exchangeMic":"BVMF","exchangeName":"B3","country":"BR","region":"latin-america","currency":"BRL","sector":"energy","industry":"integrated-oil-gas","identifiers":[{"type":"ticker","value":"PETR4","source":"b3"}],"primarySources":["b3"],"lastVerifiedAt":null},
    {"id":"index-us-spx","name":"S&P 500 Index","assetClass":"index","status":"active","ticker":"SPX","country":"US","region":"north-america","currency":"USD","identifiers":[{"type":"ticker","value":"SPX","source":"sp-global"}],"primarySources":["sp-global"],"lastVerifiedAt":null},
    {"id":"index-eu-stoxx50","name":"EURO STOXX 50","assetClass":"index","status":"active","ticker":"SX5E","country":"EU","region":"europe","currency":"EUR","identifiers":[{"type":"ticker","value":"SX5E","source":"stoxx"}],"primarySources":["stoxx"],"lastVerifiedAt":null},
    {"id":"index-jp-nikkei225","name":"Nikkei 225","assetClass":"index","status":"active","ticker":"N225","country":"JP","region":"asia-pacific","currency":"JPY","identifiers":[{"type":"ticker","value":"N225","source":"nikkei"}],"primarySources":["nikkei"],"lastVerifiedAt":null},
    {"id":"commodity-gold","name":"Gold","assetClass":"commodity","status":"active","ticker":"XAU","country":"GLOBAL","region":"global","currency":"USD","identifiers":[{"type":"ticker","value":"XAU","source":"lbma"}],"primarySources":["lbma","cme"],"lastVerifiedAt":null},
    {"id":"commodity-brent","name":"Brent Crude Oil","assetClass":"commodity","status":"active","ticker":"BRN","country":"GLOBAL","region":"global","currency":"USD","identifiers":[{"type":"ticker","value":"BRN","source":"ice"}],"primarySources":["ice","eia"],"lastVerifiedAt":null},
    {"id":"currency-eurusd","name":"Euro / U.S. Dollar","assetClass":"currency","status":"active","ticker":"EURUSD","country":"GLOBAL","region":"global","currency":"USD","identifiers":[{"type":"ticker","value":"EURUSD","source":"ecb"}],"primarySources":["ecb"],"lastVerifiedAt":null},
    {"id":"currency-usdjpy","name":"U.S. Dollar / Japanese Yen","assetClass":"currency","status":"active","ticker":"USDJPY","country":"GLOBAL","region":"global","currency":"JPY","identifiers":[{"type":"ticker","value":"USDJPY","source":"ecb"}],"primarySources":["ecb","boj"],"lastVerifiedAt":null},
    {"id":"crypto-bitcoin","name":"Bitcoin","assetClass":"crypto","status":"active","ticker":"BTC","country":"GLOBAL","region":"global","currency":"USD","identifiers":[{"type":"crypto-id","value":"bitcoin","source":"coingecko"}],"primarySources":["coingecko"],"lastVerifiedAt":null},
    {"id":"crypto-ethereum","name":"Ethereum","assetClass":"crypto","status":"active","ticker":"ETH","country":"GLOBAL","region":"global","currency":"USD","identifiers":[{"type":"crypto-id","value":"ethereum","source":"coingecko"}],"primarySources":["coingecko"],"lastVerifiedAt":null},
    {"id":"bond-us-10y","name":"United States 10-Year Government Bond","assetClass":"bond","status":"active","ticker":"US10Y","country":"US","region":"north-america","currency":"USD","identifiers":[{"type":"ticker","value":"US10Y","source":"fred"}],"primarySources":["fred","us-treasury"],"lastVerifiedAt":null}
  ]
}